COPYRIGHT
MANIFEST.in
pip-requirements.txt
setup.cfg
setup.py
curate/__init__.py
curate/actions.py
curate/builtins.py
curate/command.py
curate/rules.py
curate/work.py
curate.egg-info/PKG-INFO
curate.egg-info/SOURCES.txt
curate.egg-info/dependency_links.txt
curate.egg-info/entry_points.txt
curate.egg-info/not-zip-safe
curate.egg-info/requires.txt
curate.egg-info/top_level.txt
docs/actions.txt
docs/builtins.txt
docs/command.txt
docs/conf.py
docs/index.txt
docs/installation.txt
docs/overview.txt
docs/_static/.keep
examples/curl.n3
examples/dereference.n3
examples/groups.n3
examples/sparqlep.n3
examples/tagging.n3