Metadata-Version: 1.0
Name: curate
Version: 0.15
Summary: Curation Utilities for CKAN
Home-page: http://packages.python.org/curate/
Author: Open Knowledge Foundation
Author-email: okfn-help@lists.okfn.org
License: AGPL
Keywords: ckan rdf rdflib
Platform: UNKNOWN
Classifier: Development Status :: 3 - Alpha
Classifier: Environment :: Console
Classifier: Environment :: Web Environment
Classifier: Intended Audience :: Developers
Classifier: Intended Audience :: Information Technology
Classifier: Intended Audience :: Science/Research
Classifier: License :: OSI Approved :: GNU Affero General Public License v3
Classifier: Operating System :: POSIX
Classifier: Programming Language :: Python :: 2.6
Classifier: Topic :: Internet
Classifier: Topic :: Scientific/Engineering :: Artificial Intelligence
Classifier: Topic :: Software Development :: Libraries :: Python Modules
